TWCManager/TWCManager.py
TWCManager/TWCMaster.py
TWCManager/TWCSlave.py
TWCManager/Control/HTTPControl.py
TWCManager/Control/MQTTControl.py
TWCManager/Control/WebIPCControl.py
TWCManager/Control/static/css/styles.css
TWCManager/Control/static/js/commonUI.js
TWCManager/Control/static/js/debug.js
TWCManager/Control/static/js/settings.js
TWCManager/Control/static/js/status.js
TWCManager/Control/themes/Default/bootstrap.html.j2
TWCManager/Control/themes/Default/debug.html.j2
TWCManager/Control/themes/Default/drawChart.html.j2
TWCManager/Control/themes/Default/graphs.html.j2
TWCManager/Control/themes/Default/handle_teslalogin.html.j2
TWCManager/Control/themes/Default/jsrefresh.html.j2
TWCManager/Control/themes/Default/main.html.j2
TWCManager/Control/themes/Default/navbar.html.j2
TWCManager/Control/themes/Default/policy.html.j2
TWCManager/Control/themes/Default/request_teslalogin.html.j2
TWCManager/Control/themes/Default/schedule.html.j2
TWCManager/Control/themes/Default/settings.html.j2
TWCManager/Control/themes/Default/showCommands.html.j2
TWCManager/Control/themes/Default/showStatus.html.j2
TWCManager/Control/themes/Default/upgrade.html.j2
TWCManager/Control/themes/Default/upgradePrompt.html.j2
TWCManager/Control/themes/Default/vehicleDetail.html.j2
TWCManager/Control/themes/Default/vehicles.html.j2
TWCManager/Control/themes/Modern/bootstrap.js.html.j2
TWCManager/Control/themes/Modern/jsrefresh.html.j2
TWCManager/Control/themes/Modern/main.html.j2
TWCManager/Control/themes/Modern/master.html.j2
TWCManager/Control/themes/Modern/css/styles.css
TWCManager/EMS/DSMR.py
TWCManager/EMS/DSMRreader.py
TWCManager/EMS/Efergy.py
TWCManager/EMS/EmonCMS.py
TWCManager/EMS/Enphase.py
TWCManager/EMS/Fronius.py
TWCManager/EMS/Growatt.py
TWCManager/EMS/HASS.py
TWCManager/EMS/IotaWatt.py
TWCManager/EMS/Kostal.py
TWCManager/EMS/MQTT.py
TWCManager/EMS/OpenHab.py
TWCManager/EMS/OpenWeatherMap.py
TWCManager/EMS/P1Monitor.py
TWCManager/EMS/SmartMe.py
TWCManager/EMS/SmartPi.py
TWCManager-1.3.2.dist-info/LICENSE
TWCManager-1.3.2.dist-info/METADATA
TWCManager-1.3.2.dist-info/WHEEL
TWCManager-1.3.2.dist-info/top_level.txt
TWCManager-1.3.2.dist-info/RECORD
