Metadata-Version: 2.1
Name: TWCManager
Version: 1.3.2
Summary: Package to manage Tesla Wall Connector installations
Home-page: https://github.com/ngardiner/twcmanager
Author: Nathan Gardiner
Author-email: ngardiner@gmail.com
Keywords: tesla wall connector charger
Requires-Python: >= 3.6
License-File: LICENSE
Requires-Dist: cryptography <3.4
Requires-Dist: growattServer >=1.0.0
Requires-Dist: jinja2 >=2.11.2
Requires-Dist: ocpp
Requires-Dist: paho-mqtt >=1.5.0
Requires-Dist: psycopg2
Requires-Dist: pyjwt
Requires-Dist: pyModbusTCP >=0.1.8
Requires-Dist: pymysql
Requires-Dist: pyserial >=3.4
Requires-Dist: pyyaml
Requires-Dist: requests >=2.23.0
Requires-Dist: sentry-sdk >=0.11.2
Requires-Dist: solaredge-modbus >=0.7.0
Requires-Dist: sysv-ipc
Requires-Dist: termcolor >=1.1.0
Requires-Dist: websockets <=9.1 ; python_version == "3.6"
Requires-Dist: websockets >=9.1 ; python_version >= "3.7"
